setup.py
docs/HISTORY.txt
docs/INSTALL.txt
docs/LICENSE.GPL
docs/LICENSE.txt
docs/README.txt
docs/TODO.txt
vice/__init__.py
vice.zope2.outbound.egg-info/PKG-INFO
vice.zope2.outbound.egg-info/SOURCES.txt
vice.zope2.outbound.egg-info/dependency_links.txt
vice.zope2.outbound.egg-info/entry_points.txt
vice.zope2.outbound.egg-info/namespace_packages.txt
vice.zope2.outbound.egg-info/not-zip-safe
vice.zope2.outbound.egg-info/requires.txt
vice.zope2.outbound.egg-info/top_level.txt
vice/zope2/__init__.py
vice/zope2/outbound/__init__.py
vice/zope2/outbound/config.py
vice/zope2/outbound/configure.zcml
vice/zope2/outbound/utils.py
vice/zope2/outbound/adapters/__init__.py
vice/zope2/outbound/adapters/configure.zcml
vice/zope2/outbound/browser/__init__.py
vice/zope2/outbound/browser/configure.zcml
vice/zope2/outbound/tests/__init__.py
vice/zope2/outbound/tests/test.py