Metadata-Version: 1.0
Name: vice.zope2.outbound
Version: 1.0a1
Summary: Zope2 library for outbound syndication.
Home-page: http://www.openplans.org/projects/vice/
Author: Derek Richardson
Author-email: syndication@derekrichardson.net
License: GPL
Keywords: syndication atom rdf rss zope feeds
Platform: UNKNOWN
Classifier: Framework :: Zope2
Classifier: Programming Language :: Python
Classifier: Topic :: Software Development :: Libraries :: Python Modules
